<?xml version="1.0" encoding="utf-8" ?>
<dwsync>
<file name="de.js" server="shiftcms.net//subdomains/demo/httpdocs/" local="127697810480000000" remote="128632989600000000" />
<file name="en.js" server="shiftcms.net//subdomains/demo/httpdocs/" local="127602352100000000" remote="128632989600000000" />
<file name="fr.js" server="shiftcms.net//subdomains/demo/httpdocs/" local="127602352280000000" remote="128632989600000000" />
<file name="it.js" server="shiftcms.net//subdomains/demo/httpdocs/" local="127602352140000000" remote="128632989600000000" />
<file name="pl.js" server="shiftcms.net//subdomains/demo/httpdocs/" local="127764029180000000" remote="128632989600000000" />
<file name="de.js" server="shiftcms.net/subdomains/demo/httpdocs/" local="128478938540000000" remote="128674098600000000" />
<file name="en.js" server="shiftcms.net/subdomains/demo/httpdocs/" local="128478938540000000" remote="128674098600000000" />
<file name="es.js" server="shiftcms.net/subdomains/demo/httpdocs/" local="128484236220000000" remote="128674098600000000" />
<file name="fr.js" server="shiftcms.net/subdomains/demo/httpdocs/" local="128478938540000000" remote="128674098600000000" />
<file name="it.js" server="shiftcms.net/subdomains/demo/httpdocs/" local="128478938540000000" remote="128674098600000000" />
<file name="pl.js" server="shiftcms.net/subdomains/demo/httpdocs/" local="128478938540000000" remote="128674098600000000" />
<file name="de.js" server="shiftcms.net//subdomains/test/httpdocs/" local="128719310014675560" remote="128719373400000000" />
<file name="en.js" server="shiftcms.net//subdomains/test/httpdocs/" local="128719310019763125" remote="128719373400000000" />
<file name="es.js" server="shiftcms.net//subdomains/test/httpdocs/" local="128719310022272730" remote="128719373400000000" />
<file name="fr.js" server="shiftcms.net//subdomains/test/httpdocs/" local="128719310024860455" remote="128719373400000000" />
<file name="it.js" server="shiftcms.net//subdomains/test/httpdocs/" local="128719310034283680" remote="128719373400000000" />
<file name="pl.js" server="shiftcms.net//subdomains/test/httpdocs/" local="128719310069447445" remote="128719373400000000" />
</dwsync>